lifeguard_rabbitmq/__init__.py
lifeguard_rabbitmq/consumer.py
lifeguard_rabbitmq/context.py
lifeguard_rabbitmq/endpoints.py
lifeguard_rabbitmq/settings.py
lifeguard_rabbitmq/validations.py
lifeguard_rabbitmq/rabbitmq/__init__.py
lifeguard_rabbitmq/rabbitmq/admin.py
lifeguard_rabbitmq-1.1.1.data/scripts/lifeguard-rabbitmq-consumer
lifeguard_rabbitmq-1.1.1.dist-info/METADATA
lifeguard_rabbitmq-1.1.1.dist-info/WHEEL
lifeguard_rabbitmq-1.1.1.dist-info/top_level.txt
lifeguard_rabbitmq-1.1.1.dist-info/RECORD
